{
  "n_results": 60,
  "config_hash": "2f8a9e985010c1f6",
  "config_match": true,
  "C0": {
    "hot_absL": 1.8352369826641068,
    "ctrl_absL": 0.12436172133080098,
    "pass": true
  },
  "C1": {
    "0.25": {
      "ks": 0.14,
      "p": 0.041,
      "median_shift": 0.6150000000000002,
      "occ_chi2": 0.00337
    },
    "0.5": {
      "ks": 0.13,
      "p": 0.0675,
      "median_shift": 0.5100000000000007,
      "occ_chi2": 0.00449
    },
    "1.0": {
      "ks": 0.055,
      "p": 0.8876,
      "median_shift": 0.3600000000000003,
      "occ_chi2": 0.00011
    },
    "2.0": {
      "ks": 0.07,
      "p": 0.6837,
      "median_shift": -0.1349999999999998,
      "occ_chi2": 0.00141
    },
    "4.0": {
      "ks": 0.075,
      "p": 0.5792,
      "median_shift": 0.29000000000000004,
      "occ_chi2": 0.00309
    }
  },
  "fork_a_fpt_signature": false,
  "C2": {
    "0.25": {
      "online_mean": 0.00036005025922776425,
      "frozen_mean": 0.000492200468203414,
      "z_vs_frozen": -8.810926523962877
    },
    "0.5": {
      "online_mean": 0.00044983097006428554,
      "frozen_mean": 0.00035739154072882476,
      "z_vs_frozen": 6.863643687274091
    },
    "1.0": {
      "online_mean": 0.0003429064314978323,
      "frozen_mean": 0.0003387320040745581,
      "z_vs_frozen": 0.05618271239957842
    },
    "2.0": {
      "online_mean": 0.00037817585253040523,
      "frozen_mean": 0.0003676085548794479,
      "z_vs_frozen": 0.17547469943679364
    },
    "4.0": {
      "online_mean": 0.0003318762254831613,
      "frozen_mean": 0.0003021751183908016,
      "z_vs_frozen": 0.62452648424953
    }
  },
  "fork_b_current": true,
  "C3": {
    "slope": 0.712,
    "pass": false,
    "points": [
      [
        0.15,
        2.7
      ],
      [
        0.3,
        6.47
      ],
      [
        0.6,
        8.29
      ],
      [
        1.2,
        12.92
      ]
    ]
  },
  "C4": {
    "detail": {
      "0.5": {
        "mean_circ": 0.0003327650625511313,
        "n": 4
      },
      "1.0": {
        "mean_circ": 0.0003356870263643313,
        "n": 4
      }
    },
    "z_vs_unbiased": {
      "0.5": -0.25,
      "1.0": -0.18
    },
    "monotone": true
  },
  "fork_d_engineered": false,
  "fork_verdict": [
    "(b) non-conservative current"
  ]
}
